gs_usb/__init__.py
gs_usb/__version__.py
gs_usb/constants.py
gs_usb/gs_usb.py
gs_usb/gs_usb_frame.py
gs_usb/gs_usb_structures.py
gs_usb-0.3.0.dist-info/METADATA
gs_usb-0.3.0.dist-info/WHEEL
gs_usb-0.3.0.dist-info/top_level.txt
gs_usb-0.3.0.dist-info/RECORD
